qimpy/__init__.py
qimpy-0.0.1.dist-info/LICENSE
qimpy-0.0.1.dist-info/METADATA
qimpy-0.0.1.dist-info/WHEEL
qimpy-0.0.1.dist-info/top_level.txt
qimpy-0.0.1.dist-info/RECORD
