Metadata-Version: 2.1
Name: qimpy
Version: 0.0.1
Summary: Quantum-Integrated Multi-PhYsics
Home-page: https://qimpy.org
Author: QimPy Collaboration
Author-email: author@example.com
License: UNKNOWN
Project-URL: Bug Tracker, https://github.com/shankar1729/qimpy/issues
Platform: UNKNOWN
Classifier: Programming Language :: Python :: 3
Classifier: License :: OSI Approved :: BSD License
Classifier: Operating System :: OS Independent
Requires-Python: >=3.8
